Metadata-Version: 1.0
Name: openpromela
Version: 0.1.0
Summary: Generalized reactive(1) synthesis from Promela specifications.
Home-page: https://github.com/johnyf/openpromela
Author: Ioannis Filippidis
Author-email: jfilippidis@gmail.com
License: BSD
Platform: UNKNOWN
